{
"kinshasa": [
    {
      "nom": "Place de la Gare",
      "latitude": -4.4419311,
      "longitude": 15.2662931,
      "image": "/img/Rectangle1.png"
    },
    {
      "nom": "Stade des Martyrs",
      "latitude": -4.4009,
      "longitude": 15.2524,
      "image": "/img/Rectangle2.png"
    },
    {
      "nom": "Tour de l'Échangeur de Limete",
      "latitude": -4.32758,
      "longitude": 15.31357,
      "image": "/img/Rectangle3.png"
    },
    {
      "nom": "Palais du Peuple",
      "latitude": -4.3225,
      "longitude": 15.3219,
      "image": "/img/Rectangle4.png"
    },
    {
      "nom": "Marché de la Liberté",
      "latitude": -4.3316,
      "longitude": 15.3089,
      "image": "/img/Rectangle5.png"
    },
    {
      "nom": "Mont Ngaliema",
      "latitude": -4.3167,
      "longitude": 15.2333,
      "image": "/img/Rectangle6.png"
    },
    {
      "nom": "Université de Kinshasa",
      "latitude": -4.3777,
      "longitude": 15.2350,
      "image": "/img/Rectangle7.png"
    }
  ],

  "Matadi": [
    {
      "nom": "Pont Maréchal",
      "latitude": -5.8246,
      "longitude": 13.4912,
      "image": "/img/Rectangle1.png"
    },
    {
      "nom": "Port de Matadi",
      "latitude": -5.8075,
      "longitude": 13.4508,
      "image": "/img/Rectangle2.png"
    },
    {
      "nom": "Cathédrale Notre-Dame de Matadi",
      "latitude": -5.8169,
      "longitude": 13.4822,
      "image": "/img/Rectangle3.png"
    },
    {
      "nom": "Rochers de Diogo Cão",
      "latitude": -5.8214,
      "longitude": 13.4478,
      "image": "/img/Rectangle4.png"
    },
    {
      "nom": "Vue sur le fleuve Congo depuis Matadi",
      "latitude": -5.8183,
      "longitude": 13.4861,
      "image": "/img/Rectangle5.png"
    },
    {
      "nom": "Gare de Matadi",
      "latitude": -5.8136,
      "longitude": 13.4778,
      "image": "/img/Rectangle6.png"
    },
    {
      "nom": "Centre-ville de Matadi",
      "latitude": -5.8167,
      "longitude": 13.4833,
      "image": "/img/Rectangle7.png"
    }
  ],

  "Muanda": [
    {
      "nom": "Plage de Muanda",
      "latitude": -5.9309,
      "longitude": 12.3519,
      "image": "/img/Rectangle1.png"
    },
    {
      "nom": "Port de Muanda",
      "latitude": -5.9333,
      "longitude": 12.35,
      "image": "/img/Rectangle2.png"
    },
    {
      "nom": "Embouchure du fleuve Congo",
      "latitude": -6.0,
      "longitude": 12.4167,
      "image": "/img/Rectangle3.png"
    },
    {
      "nom": "Phare de Banana",
      "latitude": -5.9992,
      "longitude": 12.4042,
      "image": "/img/Rectangle4.png"
    },
    {
      "nom": "Village de pêcheurs à Muanda",
      "latitude": -5.925,
      "longitude": 12.355,
      "image": "/img/Rectangle5.png"
    },
    {
      "nom": "Mangroves de Muanda",
      "latitude": -5.9358,
      "longitude": 12.3425,
      "image": "/img/Rectangle6.png"
    },
    {
      "nom": "Base pétrolière offshore",
      "latitude": -5.9286,
      "longitude": 12.3472,
      "image": "/img/Rectangle7.png"
    }
  ]
  
}